jupyter_python_languageserver/__init__.py
jupyter_python_languageserver/_version.py
jupyter_python_languageserver/langserver.py
jupyter_python_languageserver-0.1.1.data/data/etc/jupyter/jupyter_notebook_config.d/jupyter_python_languageserver.json
jupyter_python_languageserver-0.1.1.dist-info/LICENSE.txt
jupyter_python_languageserver-0.1.1.dist-info/METADATA
jupyter_python_languageserver-0.1.1.dist-info/WHEEL
jupyter_python_languageserver-0.1.1.dist-info/top_level.txt
jupyter_python_languageserver-0.1.1.dist-info/RECORD
